better_menu/__init__.py
better_menu/menu.py
better_menu-1.0.13.dist-info/METADATA
better_menu-1.0.13.dist-info/WHEEL
better_menu-1.0.13.dist-info/top_level.txt
better_menu-1.0.13.dist-info/RECORD
