Metadata-Version: 2.1
Name: better-menu
Version: 1.0.13
Summary: A simple but cool menu-creation package
Home-page: https://github.com/C-JeanDev/better_menu
Author: Bilodev, C-JeanDev
Author-email: bilotta.antonio.biz@gmail.com
Keywords: python,menu,selection menu,menu selection,selection,cool menu,cli
Classifier: Development Status :: 5 - Production/Stable
Classifier: Intended Audience :: Developers
Classifier: Programming Language :: Python :: 3
Classifier: Operating System :: Unix
Classifier: Operating System :: MacOS :: MacOS X
Classifier: Operating System :: Microsoft :: Windows
Requires-Dist: print-color
